gmicloud/__init__.py
gmicloud/client.py
gmicloud/_internal/__init__.py
gmicloud/_internal/_config.py
gmicloud/_internal/_constants.py
gmicloud/_internal/_enums.py
gmicloud/_internal/_exceptions.py
gmicloud/_internal/_models.py
gmicloud/_internal/_client/__init__.py
gmicloud/_internal/_client/_artifact_client.py
gmicloud/_internal/_client/_decorator.py
gmicloud/_internal/_client/_file_upload_client.py
gmicloud/_internal/_client/_http_client.py
gmicloud/_internal/_client/_iam_client.py
gmicloud/_internal/_client/_task_client.py
gmicloud/_internal/_manager/__init__.py
gmicloud/_internal/_manager/_artifact_manager.py
gmicloud/_internal/_manager/_iam_manager.py
gmicloud/_internal/_manager/_task_manager.py
gmicloud/tests/__init__.py
gmicloud/tests/test_artifacts.py
gmicloud/tests/test_tasks.py
gmicloud/utils/uninstall_packages.py
gmicloud_ai-0.1.5.dist-info/METADATA
gmicloud_ai-0.1.5.dist-info/WHEEL
gmicloud_ai-0.1.5.dist-info/top_level.txt
gmicloud_ai-0.1.5.dist-info/RECORD
