Metadata-Version: 2.2
Name: gmicloud-ai
Version: 0.1.5
Summary: GMI Cloud Python SDK
Author-email: GMI <support@gmicloud.ai>
License: MIT
Classifier: Programming Language :: Python :: 3
Classifier: License :: OSI Approved :: MIT License
Classifier: Operating System :: OS Independent
Requires-Python: >=3.6
